postleaksNg/__init__.py
postleaksNg/__main__.py
postleaksNg/config.yml
postleaksNg-1.0.1.dist-info/LICENSE
postleaksNg-1.0.1.dist-info/METADATA
postleaksNg-1.0.1.dist-info/WHEEL
postleaksNg-1.0.1.dist-info/entry_points.txt
postleaksNg-1.0.1.dist-info/top_level.txt
postleaksNg-1.0.1.dist-info/RECORD
