Metadata-Version: 2.1
Name: postleaksNg
Version: 1.0.1
Summary: postleaksNg
Home-page: https://github.com/six2dez/postleaksNg
Author: Sébastien Copin
Author-email: cosad3s@outlook.com
License: GPL-3.0 License
Keywords: leaks,postman,osint,bugbounty
Classifier: Topic :: Internet :: WWW/HTTP :: Indexing/Search
Classifier: Topic :: Security
Classifier: Programming Language :: Python :: 3
License-File: LICENSE
Requires-Dist: requests
Requires-Dist: argparse
Requires-Dist: whispers
